[
    {
        "name": "Alto Perené",
        "student": "c5a76e2b3b7d2a9f",
        "netid": "6c17012ad508887e",
        "country": "Peru",
        "language_family": "Arawak",
        "num_consonants": 16,
        "num_vowels": 12,
        "num_phonemes": 28,
        "consonants": [
            "n",
            "t",
            "m",
            "k",
            "j",
            "s",
            "p",
            "w",
            "h",
            "ʃ",
            "tʃ",
            "ɲ",
            "ts",
            "ɾ",
            "ɴ"
        ],
        "consonant_types": [
            "affricates"
        ],
        "vowels": [
            "a",
            "e",
            "o",
            "i"
        ],
        "vowel_types": [
            "long",
            "diphthongs"
        ],
        "num_consonant_places": 8,
        "num_consonant_manners": 6,
        "syllables": [
            "C onset",
            "C coda"
        ]
    },
    {
        "name": "Bukawa",
        "student": "9cadd43cc7cbbc67",
        "netid": "589788a487cab97d",
        "country": "Papua New Guinea",
        "language_family": "Austronesian",
        "num_consonants": 34,
        "num_vowels": 8,
        "num_phonemes": 42,
        "consonants": [
            "n",
            "t",
            "m",
            "k",
            "j",
            "s",
            "p",
            "l",
            "w",
            "h",
            "b",
            "d",
            "g",
            "ŋ",
            "ʔ",
            "ɾ",
            "ʝ"
        ],
        "consonant_types": [
            "prenasalized",
            "multi-place / secondary articulation"
        ],
        "vowels": [
            "a",
            "e",
            "i",
            "u",
            "ø",
            "ɪ",
            "ʊ"
        ],
        "vowel_types": [],
        "num_consonant_places": 6,
        "num_consonant_manners": 6,
        "syllables": [
            "V",
            "C onset",
            "C coda"
        ],
        "recommend": "Yes, my grammar was great to work with",
        "morphological_type": [
            "fusional",
            "agglutinating"
        ],
        "word_formation": [
            "suffixation",
            "prefixation",
            "infixation",
            "compounding",
            "reduplication"
        ],
        "word_formation frequency": "equal affixation and other"
    },
    {
        "name": "Cherokee",
        "student": "1c936c304a35951d",
        "netid": "1b5223ffa2a9588d",
        "country": "USA (NC/OK)",
        "language_family": "Iroquoian",
        "num_consonants": 10,
        "num_vowels": 6,
        "num_phonemes": 16,
        "consonants": [
            "n",
            "m",
            "j",
            "s",
            "l",
            "w",
            "h",
            "d",
            "g",
            "ʔ",
            "dʒ",
            "dʰ",
            "gʰ"
        ],
        "consonant_types": [
            "affricates"
        ],
        "vowels": [
            "e",
            "o",
            "i",
            "u",
            "ɑ",
            "ʌ"
        ],
        "vowel_types": [
            "nasalized",
            "long"
        ],
        "num_consonant_places": 7,
        "num_consonant_manners": 7,
        "syllables": [
            "V",
            "C onset",
            "CC onset",
            "C coda"
        ],
        "recommend": "Maybe (e.g., perhaps only for a student with a linguistics background)",
        "morphological_type": [
            "fusional",
            "polysynthetic"
        ],
        "word_formation": [
            "suffixation",
            "prefixation",
            "internal change",
            "stress or tone shift"
        ],
        "word_formation frequency": "mostly prefixing"
    },
    {
        "name": "Choctaw",
        "student": "5b951991693d13e6",
        "netid": "ab824a03c9e3a651",
        "country": "United States",
        "language_family": "Muskogean",
        "num_consonants": 16,
        "num_vowels": 9,
        "num_phonemes": 25,
        "consonants": [
            "n",
            "t",
            "m",
            "k",
            "j",
            "s",
            "p",
            "l",
            "w",
            "h",
            "b",
            "ʃ",
            "ʔ",
            "tʃ",
            "f",
            "ɬ"
        ],
        "consonant_types": [
            "affricates"
        ],
        "vowels": [
            "a",
            "o",
            "i"
        ],
        "vowel_types": [
            "nasalized",
            "long"
        ],
        "num_consonant_places": 8,
        "num_consonant_manners": 7,
        "syllables": [
            "V",
            "C onset",
            "CC onset",
            "C coda",
            "CC coda"
        ],
        "recommend": "Maybe (e.g., perhaps only for a student with a linguistics background)",
        "morphological_type": [
            "agglutinating"
        ],
        "word_formation": [
            "suffixation",
            "prefixation",
            "infixation",
            "suppletion"
        ],
        "word_formation frequency": "equal prefixing and suffixing"
    },
    {
        "name": "Creek (Muskogee)",
        "student": "f73be0137076ab82",
        "netid": "c99454ebe711ebe8",
        "country": "USA",
        "language_family": "Muskogean",
        "num_consonants": 13,
        "num_vowels": 15,
        "num_phonemes": 28,
        "consonants": [
            "n",
            "t",
            "m",
            "k",
            "j",
            "s",
            "p",
            "l",
            "w",
            "h",
            "tʃ",
            "f",
            "ɬ"
        ],
        "consonant_types": [
            "affricates"
        ],
        "vowels": [
            "o",
            "i",
            "ɑ"
        ],
        "vowel_types": [
            "nasalized",
            "long",
            "diphthongs"
        ],
        "num_consonant_places": 8,
        "num_consonant_manners": 7,
        "syllables": [
            "V",
            "C onset",
            "C coda"
        ],
        "recommend": "Yes, my grammar was great to work with",
        "morphological_type": [
            "agglutinating"
        ],
        "word_formation": [
            "suffixation",
            "prefixation",
            "infixation",
            "compounding",
            "stress or tone shift"
        ],
        "word_formation frequency": "equal prefixing and suffixing"
    },
    {
        "name": "Daakaka",
        "student": "51042dfd7848d80c",
        "netid": "bbb14152852462da",
        "country": "Ambrym",
        "language_family": "Oceanic",
        "num_consonants": 18,
        "num_vowels": 14,
        "num_phonemes": 32,
        "consonants": [
            "n",
            "t",
            "m",
            "k",
            "j",
            "s",
            "p",
            "l",
            "w",
            "b",
            "d",
            "g",
            "ŋ",
            "r",
            "v"
        ],
        "consonant_types": [
            "multi-place / secondary articulation"
        ],
        "vowels": [
            "a",
            "e",
            "o",
            "i",
            "u",
            "ə",
            "ɛ",
            "ɔ"
        ],
        "vowel_types": [
            "long"
        ],
        "num_consonant_places": 6,
        "num_consonant_manners": 6,
        "syllables": [
            "V",
            "C onset",
            "CC onset",
            "C coda",
            "CC coda"
        ],
        "recommend": "Yes, my grammar was fine to work with (even if not perfect)",
        "morphological_type": [
            "analytic"
        ],
        "word_formation": [
            "suffixation",
            "prefixation",
            "infixation",
            "compounding",
            "suppletion",
            "reduplication"
        ],
        "word_formation frequency": "mostly suffixing"
    },
    {
        "name": "Kurdish",
        "student": "5d5efb2d43faa004",
        "netid": "268c107fdd3f1061",
        "country": "Iraq, Turkey, Syria",
        "language_family": "Indo-European",
        "num_consonants": 33,
        "num_vowels": 9,
        "num_phonemes": 42,
        "consonants": [
            "n",
            "t",
            "m",
            "k",
            "j",
            "s",
            "p",
            "l",
            "w",
            "h",
            "b",
            "d",
            "g",
            "ŋ",
            "ʃ",
            "ʔ",
            "f",
            "r",
            "z",
            "x",
            "v",
            "ɾ",
            "ɭ",
            "ç",
            "ʝ",
            "ɣ",
            "q",
            "ħ"
        ],
        "consonant_types": [
            "uvular / retroflex / pharyngeal",
            "affricates"
        ],
        "vowels": [
            "a",
            "e",
            "o",
            "i",
            "u",
            "ə",
            "ɯ",
            "ɪ",
            "ɔ"
        ],
        "vowel_types": [],
        "num_consonant_places": 11,
        "num_consonant_manners": 7,
        "syllables": [
            "V",
            "C onset",
            "CC onset",
            "C coda",
            "CC coda"
        ],
        "recommend": "Yes, my grammar was fine to work with (even if not perfect)",
        "morphological_type": [
            "agglutinating"
        ],
        "word_formation": [
            "suffixation",
            "prefixation",
            "infixation",
            "compounding",
            "stress or tone shift",
            "reduplication"
        ],
        "word_formation frequency": "mostly suffixing"
    },
    {
        "name": "Kuuk Thaayorre",
        "student": "f04474a5f78c75ff",
        "netid": "26483a1f20f0cbe8",
        "country": "Australia",
        "language_family": "Pama-Nyungan",
        "num_consonants": 16,
        "num_vowels": 10,
        "num_phonemes": 26,
        "consonants": [
            "n",
            "t",
            "m",
            "k",
            "j",
            "p",
            "l",
            "ŋ",
            "ʔ",
            "r",
            "ɲ",
            "ɻ",
            "c",
            "ɰ"
        ],
        "consonant_types": [
            "uvular / retroflex / pharyngeal"
        ],
        "vowels": [
            "a",
            "e",
            "o",
            "i",
            "u"
        ],
        "vowel_types": [
            "long"
        ],
        "num_consonant_places": 6,
        "num_consonant_manners": 5,
        "syllables": [
            "V",
            "C onset",
            "C coda",
            "CC coda",
            "CCC coda"
        ],
        "recommend": "Yes, my grammar was fine to work with (even if not perfect)",
        "morphological_type": [
            "agglutinating"
        ],
        "word_formation": [
            "suffixation",
            "prefixation",
            "infixation",
            "compounding",
            "stress or tone shift",
            "reduplication"
        ],
        "word_formation frequency": "mostly suffixing"
    },
    {
        "name": "Manange",
        "student": "4c3ecd2dc1412e10",
        "netid": "c2b3104824c98edc",
        "country": "Nepal",
        "language_family": "Sino-Tibetan",
        "num_consonants": 30,
        "num_vowels": 10,
        "num_phonemes": 40,
        "consonants": [
            "n",
            "t",
            "m",
            "k",
            "j",
            "s",
            "p",
            "l",
            "h",
            "ŋ",
            "ʔ",
            "tʃ",
            "ɲ",
            "ts",
            "pʰ",
            "tʰ",
            "ʈʰ",
            "kʰ",
            "ɾ",
            "ʈ",
            "ʂ",
            "ç"
        ],
        "consonant_types": [
            "uvular / retroflex / pharyngeal",
            "affricates",
            "multi-place / secondary articulation"
        ],
        "vowels": [
            "e",
            "o",
            "i",
            "u",
            "ɜ",
            "ɐ"
        ],
        "vowel_types": [
            "nasalized"
        ],
        "num_consonant_places": 7,
        "num_consonant_manners": 8,
        "syllables": [
            "V",
            "C onset",
            "CC onset",
            "C coda"
        ],
        "recommend": "Yes, my grammar was fine to work with (even if not perfect)",
        "morphological_type": [
            "isolating"
        ],
        "word_formation": [
            "suffixation",
            "prefixation",
            "compounding",
            "suppletion",
            "reduplication"
        ],
        "word_formation frequency": "mostly isolating"
    },
    {
        "name": "Maori",
        "student": "28cd3cc0828232fc",
        "netid": "7e71a72bfbac289c",
        "country": "New Zealand",
        "language_family": "Austro-Indonesian",
        "num_consonants": 10,
        "num_vowels": 15,
        "num_phonemes": 25,
        "consonants": [
            "n",
            "t",
            "m",
            "k",
            "p",
            "w",
            "h",
            "ŋ",
            "f",
            "r"
        ],
        "consonant_types": [],
        "vowels": [
            "a",
            "e",
            "o",
            "i",
            "u"
        ],
        "vowel_types": [
            "long",
            "diphthongs"
        ],
        "num_consonant_places": 6,
        "num_consonant_manners": 5,
        "syllables": [
            "C onset"
        ],
        "recommend": "Yes, my grammar was fine to work with (even if not perfect)",
        "morphological_type": [
            "fusional"
        ],
        "word_formation": [
            "suffixation",
            "prefixation",
            "compounding",
            "reduplication"
        ],
        "word_formation frequency": "equal affixation and other"
    },
    {
        "name": "Nuosu",
        "student": "8ef62b0b01c3db12",
        "netid": "a08b1d93796a0a3c",
        "country": "China",
        "language_family": "Sino-Tibetan",
        "num_consonants": 43,
        "num_vowels": 8,
        "num_phonemes": 51,
        "consonants": [
            "n",
            "t",
            "m",
            "k",
            "s",
            "p",
            "l",
            "h",
            "b",
            "d",
            "g",
            "ŋ",
            "f",
            "z",
            "ts",
            "x",
            "v",
            "pʰ",
            "tʰ",
            "kʰ",
            "dz",
            "ʂ",
            "ʐ",
            "ɣ"
        ],
        "consonant_types": [
            "uvular / retroflex / pharyngeal",
            "affricates",
            "prenasalized"
        ],
        "vowels": [
            "a",
            "o",
            "i",
            "u",
            "ɯ",
            "ɛ",
            "ɔ"
        ],
        "vowel_types": [],
        "num_consonant_places": 6,
        "num_consonant_manners": 6,
        "syllables": [
            "C onset",
            "CC onset"
        ],
        "recommend": "Yes, my grammar was fine to work with (even if not perfect)",
        "morphological_type": [
            "analytic"
        ],
        "word_formation": [
            "suffixation",
            "prefixation",
            "compounding",
            "reduplication"
        ],
        "word_formation frequency": "mostly suffixing"
    },
    {
        "name": "Nzadi",
        "student": "965011a23da5d967",
        "netid": "85f83568d73a60fc",
        "country": "Congo",
        "language_family": "Niger-Congo",
        "num_consonants": 21,
        "num_vowels": 14,
        "num_phonemes": 35,
        "consonants": [
            "n",
            "t",
            "m",
            "k",
            "j",
            "s",
            "p",
            "l",
            "w",
            "b",
            "d",
            "g",
            "f",
            "r",
            "z",
            "ts",
            "v",
            "dz"
        ],
        "consonant_types": [
            "affricates"
        ],
        "vowels": [
            "a",
            "e",
            "o",
            "i",
            "u",
            "ɜ",
            "ɔ"
        ],
        "vowel_types": [
            "long"
        ],
        "num_consonant_places": 6,
        "num_consonant_manners": 7,
        "syllables": [
            "V",
            "C onset"
        ],
        "recommend": "Yes, my grammar was fine to work with (even if not perfect)",
        "morphological_type": [
            "analytic"
        ],
        "word_formation": [
            "suffixation",
            "prefixation",
            "compounding",
            "stress or tone shift",
            "reduplication"
        ],
        "word_formation frequency": "equal prefixing and suffixing"
    },
    {
        "name": "Old Irish",
        "student": "eedf008f5d66f1ec",
        "netid": "4fa0c60924922367",
        "country": "Ireland",
        "language_family": "Indo-European",
        "num_consonants": 40,
        "num_vowels": 21,
        "num_phonemes": 61,
        "consonants": [
            "n",
            "t",
            "m",
            "k",
            "p",
            "l",
            "h",
            "b",
            "d",
            "g",
            "ŋ",
            "f",
            "r",
            "x",
            "θ",
            "ð",
            "ɣ"
        ],
        "consonant_types": [
            "multi-place / secondary articulation",
            "geminate"
        ],
        "vowels": [
            "a",
            "e",
            "o",
            "i",
            "u",
            "ə"
        ],
        "vowel_types": [
            "long",
            "diphthongs"
        ],
        "num_consonant_places": 6,
        "num_consonant_manners": 5,
        "syllables": [
            "V",
            "C onset",
            "CC onset",
            "C coda",
            "CC coda"
        ],
        "recommend": "I needed to consult multiple grammars to gain sufficient data. This was very linguistically interesting to read, but I would not recommend this course of action if the student did not have a decent knowledge of and interest in linguistics.",
        "morphological_type": [
            "fusional",
            "polysynthetic"
        ],
        "word_formation": [
            "suffixation",
            "prefixation",
            "infixation",
            "compounding",
            "suppletion",
            "reduplication"
        ],
        "word_formation frequency": "equal prefixing and suffixing"
    },
    {
        "name": "Onondaga",
        "student": "0a3c4127fec1d96e",
        "netid": "3766ee372ee8792f",
        "country": "United States",
        "language_family": "Iroquioan",
        "num_consonants": 10,
        "num_vowels": 7,
        "num_phonemes": 17,
        "consonants": [
            "n",
            "t",
            "k",
            "j",
            "s",
            "w",
            "h",
            "ʔ",
            "ts"
        ],
        "consonant_types": [
            "affricates"
        ],
        "vowels": [
            "a",
            "e",
            "o",
            "i",
            "æ"
        ],
        "vowel_types": [
            "nasalized"
        ],
        "num_consonant_places": 5,
        "num_consonant_manners": 5,
        "syllables": [
            "C onset",
            "CC onset",
            "CCC onset",
            "CCCC onset",
            "C coda",
            "CC coda",
            "CCC coda",
            "CCCC coda"
        ],
        "recommend": "Yes, my grammar was fine to work with (even if not perfect)",
        "morphological_type": [
            "agglutinating",
            "polysynthetic"
        ],
        "word_formation": [
            "suffixation",
            "prefixation",
            "compounding",
            "root-and-pattern",
            "internal change"
        ],
        "word_formation frequency": "mostly prefixing"
    },
    {
        "name": "Puyuma",
        "student": "f3621117b12d39ea",
        "netid": "16de941fb181f351",
        "country": "Taiwan",
        "language_family": "Austronesian",
        "num_consonants": 18,
        "num_vowels": 4,
        "num_phonemes": 22,
        "consonants": [
            "n",
            "t",
            "m",
            "k",
            "j",
            "s",
            "p",
            "l",
            "w",
            "b",
            "d",
            "g",
            "ŋ",
            "ʔ",
            "r",
            "ɲ",
            "ʈ",
            "ɭ"
        ],
        "consonant_types": [
            "uvular / retroflex / pharyngeal"
        ],
        "vowels": [
            "a",
            "i",
            "u",
            "ə"
        ],
        "vowel_types": [],
        "num_consonant_places": 7,
        "num_consonant_manners": 6,
        "syllables": [
            "V",
            "C onset",
            "C coda"
        ],
        "recommend": "Yes, my grammar was great to work with",
        "morphological_type": [
            "analytic",
            "fusional"
        ],
        "word_formation": [
            "suffixation",
            "prefixation",
            "infixation",
            "reduplication"
        ],
        "word_formation frequency": "mostly prefixing"
    },
    {
        "name": "Qaqet",
        "student": "26cc7b853e2cc0fc",
        "netid": "89baa243c23c4135",
        "country": "Papua New Guinea",
        "language_family": "Baining",
        "num_consonants": 16,
        "num_vowels": 10,
        "num_phonemes": 26,
        "consonants": [
            "n",
            "t",
            "m",
            "k",
            "s",
            "p",
            "l",
            "b",
            "d",
            "g",
            "ŋ",
            "r",
            "ɲ",
            "β",
            "ɽ",
            "ɣ"
        ],
        "consonant_types": [
            "prenasalized"
        ],
        "vowels": [
            "a",
            "i",
            "u",
            "ə"
        ],
        "vowel_types": [
            "diphthongs"
        ],
        "num_consonant_places": 5,
        "num_consonant_manners": 6,
        "syllables": [
            "V",
            "C onset",
            "CC onset",
            "C coda"
        ],
        "recommend": "Yes, my grammar was fine to work with (even if not perfect)",
        "morphological_type": [
            "agglutinating"
        ],
        "word_formation": [
            "suffixation",
            "prefixation",
            "suppletion",
            "reduplication"
        ],
        "word_formation frequency": "equal prefixing and suffixing"
    },
    {
        "name": "Sierra Popoluca",
        "student": "5ff58c5abe00433f",
        "netid": "3631a33bb26f35d5",
        "country": "Mexico",
        "language_family": "Mixe-Zoquean",
        "num_consonants": 12,
        "num_vowels": 12,
        "num_phonemes": 24,
        "consonants": [
            "n",
            "t",
            "m",
            "k",
            "j",
            "s",
            "p",
            "w",
            "h",
            "ŋ",
            "ʔ",
            "ts"
        ],
        "consonant_types": [
            "affricates"
        ],
        "vowels": [
            "a",
            "i",
            "u",
            "ɛ",
            "ɘ",
            "ɔ"
        ],
        "vowel_types": [
            "long"
        ],
        "num_consonant_places": 6,
        "num_consonant_manners": 5,
        "syllables": [
            "C onset",
            "CC onset",
            "C coda",
            "CC coda",
            "CCC coda"
        ],
        "recommend": "Maybe (e.g., perhaps only for a student with a linguistics background)",
        "morphological_type": [
            "agglutinating"
        ],
        "word_formation": [
            "suffixation",
            "compounding",
            "reduplication"
        ],
        "word_formation frequency": "equal affixation and other"
    },
    {
        "name": "Tamil",
        "student": "c3bd81b2cadd7a36",
        "netid": "51474e000891f722",
        "country": "India",
        "language_family": "Dravidian",
        "num_consonants": 18,
        "num_vowels": 12,
        "num_phonemes": 30,
        "consonants": [
            "n",
            "t",
            "m",
            "k",
            "j",
            "p",
            "l",
            "ŋ",
            "r",
            "ɲ",
            "ʋ",
            "ɾ",
            "ʈ",
            "ɖ",
            "ɳ",
            "ɻ",
            "ɭ",
            "c"
        ],
        "consonant_types": [
            "uvular / retroflex / pharyngeal",
            "geminate"
        ],
        "vowels": [
            "a",
            "e",
            "o",
            "i",
            "u"
        ],
        "vowel_types": [
            "long",
            "diphthongs"
        ],
        "num_consonant_places": 6,
        "num_consonant_manners": 6,
        "syllables": [
            "V",
            "C onset",
            "CC onset",
            "C coda",
            "CC coda"
        ],
        "recommend": "Maybe (e.g., perhaps only for a student with a linguistics background)",
        "morphological_type": [
            "agglutinating"
        ],
        "word_formation": [
            "suffixation",
            "compounding",
            "suppletion",
            "reduplication"
        ],
        "word_formation frequency": "mostly suffixing"
    },
    {
        "name": "Tariana",
        "student": "cc11db56536e2d42",
        "netid": "c99ad1d0ab7bc277",
        "country": "Brazil",
        "language_family": "Arawak or Maipurean",
        "num_consonants": 24,
        "num_vowels": 15,
        "num_phonemes": 39,
        "consonants": [
            "n",
            "t",
            "m",
            "k",
            "s",
            "p",
            "l",
            "w",
            "h",
            "b",
            "d",
            "g",
            "tʃ",
            "ɲ",
            "pʰ",
            "tʰ",
            "dʰ",
            "ʈʰ",
            "kʰ"
        ],
        "consonant_types": [
            "affricates"
        ],
        "vowels": [
            "e",
            "i",
            "u",
            "ɑ",
            "ɨ",
            "ɵ"
        ],
        "vowel_types": [
            "nasalized",
            "long"
        ],
        "num_consonant_places": 8,
        "num_consonant_manners": 7,
        "syllables": [
            "V",
            "C onset",
            "CC onset",
            "C coda"
        ],
        "recommend": "Yes, my grammar was fine to work with (even if not perfect)",
        "morphological_type": [
            "agglutinating"
        ],
        "word_formation": [
            "suffixation",
            "prefixation",
            "compounding",
            "internal change",
            "suppletion",
            "stress or tone shift"
        ],
        "word_formation frequency": "mostly suffixing"
    },
    {
        "name": "Upper Necaxa Totonac",
        "student": "b451b862416f57da",
        "netid": "900f4dae43b7c1b6",
        "country": "Mexico",
        "language_family": "Totonac–Tepehua",
        "num_consonants": 17,
        "num_vowels": 5,
        "num_phonemes": 22,
        "consonants": [
            "n",
            "t",
            "m",
            "k",
            "s",
            "p",
            "w",
            "ŋ",
            "ʃ",
            "ʔ",
            "tʃ",
            "ɲ",
            "ts",
            "x",
            "ɾ",
            "ɻ"
        ],
        "consonant_types": [
            "affricates"
        ],
        "vowels": [
            "a",
            "e",
            "o",
            "i",
            "u"
        ],
        "vowel_types": [
            "long"
        ],
        "num_consonant_places": 8,
        "num_consonant_manners": 6,
        "syllables": [
            "V",
            "C onset",
            "CC onset",
            "C coda",
            "CC coda"
        ],
        "recommend": "Yes, my grammar was fine to work with (even if not perfect)",
        "morphological_type": [
            "fusional"
        ],
        "word_formation": [
            "suffixation",
            "prefixation",
            "compounding",
            "reduplication"
        ],
        "word_formation frequency": "equal prefixing and suffixing"
    },
    {
        "name": "Western Garrwa",
        "student": "c90517195d7898ad",
        "netid": "99e28e7f10e9eef1",
        "country": "Australia",
        "language_family": "Australian",
        "num_consonants": 14,
        "num_vowels": 3,
        "num_phonemes": 17,
        "consonants": [
            "n",
            "m",
            "k",
            "j",
            "l",
            "w",
            "b",
            "d",
            "ŋ",
            "r",
            "ɲ",
            "ɹ",
            "ɟ",
            "ʎ"
        ],
        "consonant_types": [],
        "vowels": [
            "a",
            "ɪ",
            "ʊ"
        ],
        "vowel_types": [],
        "num_consonant_places": 5,
        "num_consonant_manners": 5,
        "syllables": [
            "C onset"
        ],
        "recommend": "Yes, my grammar was fine to work with (even if not perfect)",
        "morphological_type": [
            "agglutinating"
        ],
        "word_formation": [
            "suffixation",
            "prefixation",
            "compounding",
            "reduplication"
        ],
        "word_formation frequency": "mostly suffixing"
    }
]